Workbook

Sheet Resumo
A1: Resumo de custos e preço sugerido
A3: CUSTO MENSAL
A4: Custo fixo (planos + domínio) | B4: =(Calculo!$I$4+Calculo!$I$6+Calculo!$I$11+Calculo!$I$13) | C4: Vercel Pro + Supabase Pro + rateio do domínio
A5: Custo variável (excedentes de uso) | B5: =Calculo!$I$14-(Calculo!$I$4+Calculo!$I$6+Calculo!$I$11+Calculo!$I$13) | C5: Storage, egress, banco, MAU, e-mails acima do incluído
A6: Custo total por mês (R$) | B6: =Calculo!$I$14
A7: Custo total por mês (US$) | B7: =Calculo!$H$14
A8: Custo total por ano (R$) | B8: =Calculo!$I$14*12
A10: PREÇO A COBRAR POR EVENTO
A11: Eventos ativos por mês | B11: =Premissas!$B$7 | C11: vem das Premissas
A12: Custo de infraestrutura por evento (R$) | B12: =Calculo!$I$14/Premissas!$B$7 | C12: custo total do mês rateado pelos eventos
A13: Margem desejada | B13: =Premissas!$B$17 | C13: vem das Premissas (200% = cobra 3x o custo)
A14: PREÇO SUGERIDO POR EVENTO (R$) | B14: =Calculo!$I$21 | C14: só cobre infra + margem — some por cima montagem, design e suporte
A15: Faturamento mensal sugerido (R$) | B15: =Calculo!$I$21*Premissas!$B$7 | C15: preço por evento x nº de eventos
A16: Lucro mensal estimado (R$) | B16: =Calculo!$I$21*Premissas!$B$7-Calculo!$I$14 | C16: faturamento - custo total de infra
A17: → Para simular por nº de convidados, veja a aba 'Simulacao'
A19: CUSTO ÚNICO INICIAL
A20: Registro do domínio (1º ano, R$) | B20: =40 | C20: renova todo ano
A22: ALERTAS
A23: Resend — média de e-mails por dia | B23: =Calculo!$B$11/30 | C23: limite do Free é 100/dia
A24: Status do limite diário do Resend | B24: =IF(Calculo!$B$11/30>100,"ESTOURA 100/dia — precisa do Pro","dentro do Free (100/dia)")
A25: Status do limite mensal do Resend | B25: =IF(Calculo!$B$11>3000,"acima de 3.000/mês — precisa do Pro","dentro do Free")
A26: Vercel | B26: =IF(Premissas!$B$4=1,"uso comercial — Hobby não é permitido, use Pro","Hobby ok")
A27: Supabase | B27: =IF(Premissas!$B$5=1,"Pro — projeto não pausa e tem backup","Free — projeto PAUSA após 7 dias inativo")
A29: Pagamentos (se ativar) — taxa estimada/mês (R$) | B29: =Calculo!$I$16 | C29: ≈4,99% do valor de presentes; descontada do repasse ao cliente, não é seu custo
A31: Observações:
A32: 1. Este modelo cobre APENAS os serviços de infraestrutura. O preço final ao cliente deve somar: horas de montagem da página, design, suporte durante o evento e lucro.
A33: 2. Vercel e Supabase têm plano gratuito, mas para uso comercial/produção o realista é Vercel Pro (US$ 20) + Supabase Pro (US$ 25) = base fixa de ~US$ 45/mês.
A34: 3. Resend cabe no plano gratuito enquanto o volume for < 100 e-mails/dia e < 3.000/mês. Acima disso, US$ 20/mês.
A35: 4. Custos de infra são compartilhados entre todos os eventos do mês — quanto mais eventos, menor o custo por evento.
A36: 5. Câmbio, volumes e margem são editáveis na aba Premissas (células amarelas). Tudo recalcula automaticamente.
A37: 6. Preços dos serviços verificados em setembro/2026.

Sheet Simulacao
A1: Simulação de um evento — quanto ele custa em infra e por quanto cobrar
A3: ENTRADAS
A4: Convidados neste evento | B4: 100 | C4: principal variável — mexa aqui
A5: E-mails por convidado | B5: =Premissas!$B$9 | C5: convite + lembrete + confirmação (Premissas)
A6: E-mails transacionais extras (acesso, recibos) | B6: =Premissas!$B$10 | C6: Premissas
A7: Mídia enviada no evento (MB) | B7: =Premissas!$B$11 | C7: fotos/vídeos no Storage (Premissas)
A8: Meses que a mídia fica retida | B8: =Premissas!$B$12 | C8: Premissas
A9: Egress do evento (GB) | B9: 3 | C9: tráfego da página + downloads de mídia
A10: Câmbio USD-BRL | B10: =Premissas!$B$3 | C10: Premissas
A11: Eventos/mês (p/ ratear custo fixo) | B11: =Premissas!$B$7 | C11: Premissas
A12: Margem desejada | B12: =Premissas!$B$17 | C12: Premissas
A13: Custo de montagem/design/suporte (R$) | B13: 0 | C13: seu trabalho — some se quiser o preço cheio
A15: TAXAS MARGINais (quanto cada unidade a mais custa)
A16: Custo marginal por e-mail (US$) | B16: =IF(Calculo!$F$11>0,0.0009,0) | C16: 0 enquanto está no Resend Free; US$ 0,90/1000 depois de entrar no Pro
A17: Custo marginal de storage US$/GB/mês | B17: =IF(Calculo!$G$7>0,0.021,0) | C17: 0 enquanto cabe nos 100 GB do Supabase Pro; US$ 0,021 depois
A18: Custo marginal de egress US$/GB | B18: =IF(Calculo!$G$8>0,0.09,0) | C18: 0 enquanto cabe nos 250 GB do Supabase Pro; US$ 0,09 depois
A20: RESULTADO DESTE EVENTO
A21: E-mails disparados no evento | B21: =$B$4*$B$5+$B$6
A22: Storage acumulado do evento (GB·mês) | B22: =($B$7/1024)*$B$8
A23: Custo variável do evento (US$) | B23: =($B$4*$B$5+$B$6)*$B$16+(($B$7/1024)*$B$8)*$B$17+$B$9*$B$18
A24: Custo variável do evento (R$) | B24: =B23*$B$10
A25: Rateio do custo fixo mensal (R$) | B25: =(Calculo!$I$4+Calculo!$I$6+Calculo!$I$11+Calculo!$I$13)/$B$11
A26: CUSTO TOTAL DO EVENTO EM INFRA (R$) | B26: =B24+B25
A27: Preço só p/ cobrir infra + margem (R$) | B27: =B26*(1+$B$12)
A28: PREÇO FINAL SUGERIDO — com montagem (R$) | B28: =B26*(1+$B$12)+$B$13
A31: TABELA — varie o nº de convidados
A32: Convidados | B32: E-mails | C32: Custo variável (R$) | D32: Rateio fixo (R$) | E32: Custo total infra (R$) | F32: Preço final sugerido (R$)
A33: 25 | B33: =A33*$B$5+$B$6 | C33: =((A33*$B$5+$B$6)*$B$16+(($B$7/1024)*$B$8)*$B$17+$B$9*$B$18)*$B$10 | D33: =(Calculo!$I$4+Calculo!$I$6+Calculo!$I$11+Calculo!$I$13)/$B$11 | E33: =C33+D33 | F33: =E33*(1+$B$12)+$B$13
A34: 50 | B34: =A34*$B$5+$B$6 | C34: =((A34*$B$5+$B$6)*$B$16+(($B$7/1024)*$B$8)*$B$17+$B$9*$B$18)*$B$10 | D34: =(Calculo!$I$4+Calculo!$I$6+Calculo!$I$11+Calculo!$I$13)/$B$11 | E34: =C34+D34 | F34: =E34*(1+$B$12)+$B$13
A35: 75 | B35: =A35*$B$5+$B$6 | C35: =((A35*$B$5+$B$6)*$B$16+(($B$7/1024)*$B$8)*$B$17+$B$9*$B$18)*$B$10 | D35: =(Calculo!$I$4+Calculo!$I$6+Calculo!$I$11+Calculo!$I$13)/$B$11 | E35: =C35+D35 | F35: =E35*(1+$B$12)+$B$13
A36: 100 | B36: =A36*$B$5+$B$6 | C36: =((A36*$B$5+$B$6)*$B$16+(($B$7/1024)*$B$8)*$B$17+$B$9*$B$18)*$B$10 | D36: =(Calculo!$I$4+Calculo!$I$6+Calculo!$I$11+Calculo!$I$13)/$B$11 | E36: =C36+D36 | F36: =E36*(1+$B$12)+$B$13
A37: 150 | B37: =A37*$B$5+$B$6 | C37: =((A37*$B$5+$B$6)*$B$16+(($B$7/1024)*$B$8)*$B$17+$B$9*$B$18)*$B$10 | D37: =(Calculo!$I$4+Calculo!$I$6+Calculo!$I$11+Calculo!$I$13)/$B$11 | E37: =C37+D37 | F37: =E37*(1+$B$12)+$B$13
A38: 200 | B38: =A38*$B$5+$B$6 | C38: =((A38*$B$5+$B$6)*$B$16+(($B$7/1024)*$B$8)*$B$17+$B$9*$B$18)*$B$10 | D38: =(Calculo!$I$4+Calculo!$I$6+Calculo!$I$11+Calculo!$I$13)/$B$11 | E38: =C38+D38 | F38: =E38*(1+$B$12)+$B$13
A39: 300 | B39: =A39*$B$5+$B$6 | C39: =((A39*$B$5+$B$6)*$B$16+(($B$7/1024)*$B$8)*$B$17+$B$9*$B$18)*$B$10 | D39: =(Calculo!$I$4+Calculo!$I$6+Calculo!$I$11+Calculo!$I$13)/$B$11 | E39: =C39+D39 | F39: =E39*(1+$B$12)+$B$13
A40: 500 | B40: =A40*$B$5+$B$6 | C40: =((A40*$B$5+$B$6)*$B$16+(($B$7/1024)*$B$8)*$B$17+$B$9*$B$18)*$B$10 | D40: =(Calculo!$I$4+Calculo!$I$6+Calculo!$I$11+Calculo!$I$13)/$B$11 | E40: =C40+D40 | F40: =E40*(1+$B$12)+$B$13
A42: Obs.: o custo variável de um evento só aparece de verdade quando a operação já estourou o Free (Resend Pro) ou o incluído do Supabase Pro. Abaixo desse ponto, o custo real do evento é quase só o rateio do custo fixo mensal.

Sheet Premissas
A1: Premissas — ajuste os valores em amarelo
A3: Câmbio USD - BRL | B3: 5.4 | C3: Cotação usada para converter os serviços (cobrados em US$)
A4: Uso comercial? (Vercel Hobby proíbe) 1=sim / 0=não | B4: 1 | C4: Se 1, entra no Vercel Pro (US$ 20/mês). O plano Hobby é gratuito mas veda uso comercial.
A5: Produção sem pausa + backup? (Supabase Pro) 1/0 | B5: 1 | C5: Se 1, entra no Supabase Pro (US$ 25/mês). O Free pausa o projeto após 7 dias inativo e não tem backup.
A7: Eventos ativos por mês | B7: 10 | C7: Quantas páginas/eventos rodando simultaneamente
A8: Convidados médios por evento | B8: 80
A9: E-mails por convidado (convite + lembrete + confirmação) | B9: 3
A10: E-mails transacionais extras por evento (acesso painel, recibos) | B10: 12
A11: Mídia enviada por evento (MB) | B11: 500 | C11: Fotos/vídeos no Storage do Supabase
A12: Meses que a mídia fica retida | B12: 6 | C12: Storage acumula enquanto os arquivos não são apagados
A13: Banda / egress total por mês (GB) | B13: 20 | C13: Tráfego de saída (páginas + download de mídia)
A14: Tamanho do banco de dados (GB) | B14: 0.5
A15: MAU — clientes + convidados autenticados por mês | B15: 300 | C15: Usuários que fazem login via magic link
A17: Margem desejada sobre o custo (%) | B17: 2 | C17: 200% = cobra 3x o custo. Ajuste conforme o mercado.
A18: Ticket médio de presentes por evento (R$) — opcional | B18: 2000 | C18: Só para estimar a taxa do provedor de pagamento (repassada)

Sheet Servicos
A1: Serviços usados pela plataforma — o que é grátis e o que passa a custar
A3: Serviço | B3: Função no projeto | C3: Plano hoje | D3: O free tier inclui | E3: Começa a pagar quando... | F3: Próximo plano (preço/mês) | G3: Preço acima do incluído
A4: Vercel | B4: Hospedagem do Next.js 16 (SSR, rotas de API, cron da fila de e-mail) | C4: Hobby (grátis) | D4: 100 GB de banda, 1 mi de invocações de função, 4 h de CPU ativa, HTTPS e deploy automático | E4: Uso comercial (proibido no Hobby) OU banda > 100 GB/mês | F4: Pro — US$ 20/mês por assento (inclui 1 TB de banda, 10 mi de edge requests) | G4: Banda além de 1 TB: US$ 0,15/GB. Sem overage no Hobby (corta ao atingir o teto).
A5: Supabase | B5: Postgres, Auth (magic link), Storage de mídia, Realtime, Edge Functions, pg_cron/pg_net | C5: Free | D5: 500 MB de banco, 1 GB de Storage, 5 GB de egress, 50 mil MAU, 500 mil invocações de edge function, 2 projetos | E5: Banco > 500 MB, Storage > 1 GB, egress > 5 GB, OU precisa de backup / projeto sem pausa (pausa após 7 dias inativo) | F5: Pro — US$ 25/mês (8 GB de banco, 100 GB de Storage, 250 GB de egress, 100 mil MAU, backup 7 dias) | G5: Banco: US$ 0,125/GB · Storage: US$ 0,021/GB · Egress: US$ 0,09/GB · MAU extra: US$ 0,00325 cada
A6: Resend | B6: E-mail transacional: convite, lembrete/confirmação de RSVP, acesso ao painel, recibo de presente | C6: Free | D6: 3.000 e-mails/mês, limite de 100/dia, 1 domínio verificado | E6: Mais de 100 e-mails/dia OU mais de 3.000 e-mails/mês | F6: Pro — US$ 20/mês (50.000 e-mails/mês, domínios ilimitados) | G6: Acima de 50.000: US$ 0,90 por 1.000 e-mails
A7: Domínio | B7: DNS do site + registros SPF/DKIM/DMARC exigidos pelo Resend para enviar e-mail | C7: Pago (obrigatório) | D7: — | E7: Sempre — é o registro anual do domínio | F7: Registro .com.br ≈ R$ 40/ano (~R$ 3,33/mês). .com ≈ US$ 12/ano. | G7: Renovação anual
A8: Provedor de pagamento (futuro) | B8: Checkout de presentes / pagamentos — hoje roda um mock, sem cobrança real | C8: Mock (inativo) | D8: Sem custo enquanto for mock | E8: Ao conectar um provedor real e processar dinheiro de verdade | F8: Sem mensalidade — cobra por transação | G8: Mercado Pago ≈ 4,99% por transação · Stripe ≈ 3,99% + R$ 0,39 (taxa descontada do repasse ao cliente)
A9: Supabase Auth (e-mail de login) | B9: Envio do magic link de autenticação — separado da fila do Resend | C9: Incluído no Supabase | D9: ~2 e-mails/hora no SMTP embutido (bom só para teste) | E9: Em produção recomenda-se SMTP próprio (o mesmo Resend) — sem custo adicional além do Resend | F9: — | G9: —
A11: Preços verificados em set/2026 (páginas oficiais Vercel, Supabase, Resend). Valores podem mudar; reconfira antes de fechar contrato.

Sheet Calculo
A1: Cálculo do custo mensal (a partir das Premissas)
A3: Item | B3: Uso estimado | C3: Unidade | D3: Incluído | E3: Excedente | F3: Custo plano (US$) | G3: Custo excedente (US$) | H3: Total US$/mês | I3: Total R$/mês
A4: Vercel — plano de hospedagem | F4: =IF(Premissas!$B$4=1,20,0) | G4: =0 | H4: =F4+G4 | I4: =H4*Premissas!$B$3
A5: Vercel — banda excedente | B5: =Premissas!$B$13 | C5: GB/mês | D5: =IF(Premissas!$B$4=1,1024,100) | E5: =MAX(0,B5-D5) | F5: =0 | G5: =MAX(0,B5-D5)*0.15 | H5: =F5+G5 | I5: =H5*Premissas!$B$3
A6: Supabase — plano | F6: =IF(Premissas!$B$5=1,25,0) | G6: =0 | H6: =F6+G6 | I6: =H6*Premissas!$B$3
A7: Supabase — Storage (mídia) excedente | B7: =(Premissas!$B$7*Premissas!$B$11*Premissas!$B$12/1024) | C7: GB | D7: =IF(Premissas!$B$5=1,100,1) | E7: =MAX(0,B7-D7) | F7: =0 | G7: =MAX(0,B7-D7)*0.021 | H7: =F7+G7 | I7: =H7*Premissas!$B$3
A8: Supabase — egress excedente | B8: =Premissas!$B$13 | C8: GB/mês | D8: =IF(Premissas!$B$5=1,250,5) | E8: =MAX(0,B8-D8) | F8: =0 | G8: =MAX(0,B8-D8)*0.09 | H8: =F8+G8 | I8: =H8*Premissas!$B$3
A9: Supabase — banco de dados excedente | B9: =Premissas!$B$14 | C9: GB | D9: =IF(Premissas!$B$5=1,8,0.5) | E9: =MAX(0,B9-D9) | F9: =0 | G9: =MAX(0,B9-D9)*0.125 | H9: =F9+G9 | I9: =H9*Premissas!$B$3
A10: Supabase — MAU excedente | B10: =Premissas!$B$15 | C10: usuários/mês | D10: =IF(Premissas!$B$5=1,100000,50000) | E10: =MAX(0,B10-D10) | F10: =0 | G10: =MAX(0,B10-D10)*0.00325 | H10: =F10+G10 | I10: =H10*Premissas!$B$3
A11: Resend — plano | B11: =(Premissas!$B$7*(Premissas!$B$8*Premissas!$B$9+Premissas!$B$10)) | C11: e-mails/mês | D11: =3000 | E11: =MAX(0,B11-D11) | F11: =IF(B11>3000,20,0) | G11: =0 | H11: =F11+G11 | I11: =H11*Premissas!$B$3
A12: Resend — e-mails acima do plano Pro | B12: =(Premissas!$B$7*(Premissas!$B$8*Premissas!$B$9+Premissas!$B$10)) | C12: e-mails/mês | D12: =50000 | E12: =MAX(0,B12-D12) | F12: =0 | G12: =IF(B12>50000,ROUNDUP((B12-50000)/1000,0)*0.9,0) | H12: =F12+G12 | I12: =H12*Premissas!$B$3
A13: Domínio (.com.br) — rateio mensal | B13: 40 | C13: R$/ano | H13: =I13/Premissas!$B$3 | I13: =B13/12
A14: TOTAL INFRAESTRUTURA | H14: =SUM(H4:H13) | I14: =SUM(I4:I13)
A16: Pagamentos (futuro) — taxa repassada, NÃO entra no total de infra | B16: =Premissas!$B$7*Premissas!$B$18 | C16: R$ GMV/mês | I16: =B16*0.0499
A18: PREÇO A COBRAR POR EVENTO
A19: Custo de infra por evento (R$) | I19: =I14/Premissas!$B$7
A20: Margem aplicada (Premissas) | I20: =Premissas!$B$17
A21: PREÇO SUGERIDO POR EVENTO (R$) | I21: =I19*(1+Premissas!$B$17)
